teflo_webhooks_notification_plugin/__init__.py
teflo_webhooks_notification_plugin/webhooks_notification_plugin.py
teflo_webhooks_notification_plugin/files/schema.yml
teflo_webhooks_notification_plugin/templates/gchat_onstart_template.jinja
teflo_webhooks_notification_plugin/templates/gchat_template.jinja
teflo_webhooks_notification_plugin/templates/generic_template.jinja
teflo_webhooks_notification_plugin/templates/slack_onstart_template.jinja
teflo_webhooks_notification_plugin/templates/slack_template.jinja
teflo_webhooks_notification_plugin-2.0.1.dist-info/AUTHORS
teflo_webhooks_notification_plugin-2.0.1.dist-info/LICENSE
teflo_webhooks_notification_plugin-2.0.1.dist-info/METADATA
teflo_webhooks_notification_plugin-2.0.1.dist-info/WHEEL
teflo_webhooks_notification_plugin-2.0.1.dist-info/entry_points.txt
teflo_webhooks_notification_plugin-2.0.1.dist-info/top_level.txt
teflo_webhooks_notification_plugin-2.0.1.dist-info/RECORD
