Metadata-Version: 2.1
Name: teflo-webhooks-notification-plugin
Version: 2.0.1
Summary: teflo's chat notifier for teflo notifications
Home-page: UNKNOWN
Author: Red Hat Inc
License: UNKNOWN
Platform: UNKNOWN
Classifier: Development Status :: 2 - Pre-Alpha
Classifier: Intended Audience :: Developers
Classifier: Natural Language :: English
Classifier: License :: OSI Approved :: GNU Lesser General Public License v3 (LGPLv3)
Classifier: Programming Language :: Python
Classifier: Programming Language :: Python :: 3.6
License-File: LICENSE
License-File: AUTHORS
Requires-Dist: httplib2
